bws_sdk/__init__.py
bws_sdk/bws_types.py
bws_sdk/client.py
bws_sdk/crypto.py
bws_sdk/errors.py
bws_sdk/token.py
bws_sdk-2.0.0.dist-info/METADATA
bws_sdk-2.0.0.dist-info/WHEEL
bws_sdk-2.0.0.dist-info/licenses/LICENSE
bws_sdk-2.0.0.dist-info/RECORD
