Metadata-Version: 2.4
Name: bws-sdk
Version: 2.0.0
Summary: pure python implimentation of the bw secrets api
License: MIT
License-File: LICENSE
Author: rippleFCL
Author-email: github@ripple.contact
Requires-Python: >=3.11.0,<3.14.0
Classifier: License :: OSI Approved :: MIT License
Classifier: Programming Language :: Python :: 3
Classifier: Programming Language :: Python :: 3.11
Classifier: Programming Language :: Python :: 3.12
Classifier: Programming Language :: Python :: 3.13
Requires-Dist: cryptography (>=45.0.5,<46.0.0)
Requires-Dist: pbkdf2 (>=1.3,<2.0)
Requires-Dist: pydantic (>=2.11.7,<3.0.0)
Requires-Dist: pyjwt (>=2.10.1,<3.0.0)
Requires-Dist: requests (>=2.32.4,<3.0.0)
